dataverse_client_python-0.1.0.dist-info/licenses/LICENSE
dataverse_sdk/__init__.py
dataverse_sdk/__version__.py
dataverse_sdk/auth.py
dataverse_sdk/client.py
dataverse_sdk/config.py
dataverse_sdk/error_codes.py
dataverse_sdk/errors.py
dataverse_sdk/http.py
dataverse_sdk/odata.py
dataverse_sdk/odata_pandas_wrappers.py
dataverse_sdk/odata_upload_files.py
dataverse_client_python-0.1.0.dist-info/METADATA
dataverse_client_python-0.1.0.dist-info/WHEEL
dataverse_client_python-0.1.0.dist-info/top_level.txt
dataverse_client_python-0.1.0.dist-info/RECORD
