Metadata-Version: 2.4
Name: dataverse-client-python
Version: 0.1.0
Summary: Python SDK for Microsoft Dataverse
Author: Microsoft Corporation
License-Expression: MIT
Project-URL: Homepage, https://github.com/microsoft/PowerPlatform-DataverseClient-Python
Classifier: Programming Language :: Python :: 3.10
Classifier: Programming Language :: Python :: 3.11
Classifier: Programming Language :: Python :: 3.12
Classifier: Programming Language :: Python :: 3.13
Classifier: Operating System :: OS Independent
Requires-Python: >=3.10
License-File: LICENSE
Requires-Dist: azure-identity>=1.17.0
Requires-Dist: azure-core>=1.30.2
Requires-Dist: requests>=2.32.0
Requires-Dist: pandas>=2.2.0
Dynamic: license-file
